brain_agent/__init__.py
brain_agent/brain_agent.py
brain_agent/config.py
brain_agent/logger.py
brain_agent/manager_tools.py
brain_agent/query_brain_tool.py
brain_agent/replicants.py
brain_agent/run_brain_agent.py
brain_agent/seed_brain_registries.py
brain_agent/tools.py
brain_agent-0.1.4.dist-info/METADATA
brain_agent-0.1.4.dist-info/WHEEL
brain_agent-0.1.4.dist-info/entry_points.txt
brain_agent-0.1.4.dist-info/top_level.txt
brain_agent-0.1.4.dist-info/RECORD
