Metadata-Version: 2.4
Name: brain-agent
Version: 0.1.4
Summary: Cognitive processing system for HEAVEN - Handles knowledge synthesis across any corpus size
Author: HEAVEN Team
Author-email: HEAVEN Team <heaven@example.com>
License: MIT
Project-URL: Homepage, https://github.com/sancovp/brain-agent
Project-URL: Repository, https://github.com/sancovp/brain-agent.git
Project-URL: Documentation, https://brain-agent.readthedocs.io
Project-URL: Issues, https://github.com/sancovp/brain-agent/issues
Classifier: Development Status :: 3 - Alpha
Classifier: Intended Audience :: Developers
Classifier: License :: OSI Approved :: MIT License
Classifier: Programming Language :: Python :: 3
Classifier: Programming Language :: Python :: 3.10
Classifier: Programming Language :: Python :: 3.11
Classifier: Topic :: Software Development :: Libraries :: Python Modules
Classifier: Topic :: Scientific/Engineering :: Artificial Intelligence
Requires-Python: >=3.10
Requires-Dist: heaven-framework>=0.1.0
Provides-Extra: dev
Requires-Dist: pytest>=7.0; extra == "dev"
Requires-Dist: pytest-asyncio>=0.21; extra == "dev"
Requires-Dist: black>=23.0; extra == "dev"
Requires-Dist: ruff>=0.1.0; extra == "dev"
Dynamic: author
Dynamic: requires-python
